Workbook

Sheet Data
A1: Annual-report data (standalone) - figures exactly as printed
A2: Company: | B2: Britannia Industries Limited | C2: Unit (check the page header, e.g. Rs crore): | F2: Rs crore
A3: Yellow cells = you fill them in (blue text = typed numbers). Grey row = format example only, not real data.
A4: If the same year appears in two reports with different numbers, use the newer report and write the reason in column H.
A5: EXAMPLE (not real): Revenue from operations | B5: P&L | C5: 1000 | D5: 1100 | E5: 1200 | F5: Annual Report FY2025-26 | G5: 140 | H5: Delete nothing here; just copy the format
A7: Line item | B7: Statement | C7: FY2023-24 | D7: FY2024-25 | E7: FY2025-26 | F7: Report (file name / year) | G7: Page no. | H7: Notes
A8: Revenue from operations | B8: P&L | C8: 16186.08 | D8: 17295.92 | E8: 18445.82 | F8: AR 2023-24 / 2024-25 / 2025-26 | G8: FY24 p.148; FY25 p.172; FY26 p.173 | H8: Total line (Sale of goods + Other operating revenues)
A9: Other income | B9: P&L | C9: 210.11 | D9: 250.68 | E9: 318.44 | F9: AR 2023-24 / 2024-25 / 2025-26 | G9: FY24 p.148; FY25 p.172; FY26 p.173
A10: Cost of materials consumed | B10: P&L | C10: 7394.74 | D10: 8608.64 | E10: 9045.68 | F10: AR 2023-24 / 2024-25 / 2025-26 | G10: FY24 p.148; FY25 p.172; FY26 p.173
A11: Purchases of stock-in-trade | B11: P&L | C11: 2033.36 | D11: 1993.16 | E11: 2028.01 | F11: AR 2023-24 / 2024-25 / 2025-26 | G11: FY24 p.148; FY25 p.172; FY26 p.173
A12: Changes in inventories of finished goods, WIP and stock-in-trade | B12: P&L | C12: 0.01 | D12: -67.96 | E12: -21.42 | F12: AR 2023-24 / 2024-25 / 2025-26 | G12: FY24 p.148; FY25 p.172; FY26 p.173
A13: Employee benefits expense | B13: P&L | C13: 565.28 | D13: 554.7 | E13: 667.47 | F13: AR 2023-24 / 2024-25 / 2025-26 | G13: FY24 p.148; FY25 p.172; FY26 p.173
A14: Finance costs | B14: P&L | C14: 151.4 | D14: 137.1 | E14: 110.8 | F14: AR 2023-24 / 2024-25 / 2025-26 | G14: FY24 p.148; FY25 p.172; FY26 p.173
A15: Depreciation and amortisation expense | B15: P&L | C15: 271.19 | D15: 284.67 | E15: 305.34 | F15: AR 2023-24 / 2024-25 / 2025-26 | G15: FY24 p.148; FY25 p.172; FY26 p.173
A16: Other expenses | B16: P&L | C16: 3121.87 | D16: 3143.73 | E16: 3335.04 | F16: AR 2023-24 / 2024-25 / 2025-26 | G16: FY24 p.148; FY25 p.172; FY26 p.173
A17: Total expenses | B17: P&L | C17: 13537.85 | D17: 14654.04 | E17: 15470.92 | F17: AR 2023-24 / 2024-25 / 2025-26 | G17: FY24 p.148; FY25 p.172; FY26 p.173
A18: Exceptional items (+ gain / - loss; enter 0 if none) | B18: P&L | C18: -2.9 | D18: -24.79 | E18: 0 | F18: AR 2023-24 / 2024-25 / 2025-26 | G18: FY24 p.148; FY25 p.172; FY26 p.173 | H18: Report shows Expense; entered negative. FY26 shows a dash = 0
A19: Profit before tax | B19: P&L | C19: 2855.44 | D19: 2867.77 | E19: 3293.34 | F19: AR 2023-24 / 2024-25 / 2025-26 | G19: FY24 p.148; FY25 p.172; FY26 p.173
A20: Tax expense (current + deferred) | B20: P&L | C20: 773.39 | D20: 737.05 | E20: 731.62 | F20: AR 2023-24 / 2024-25 / 2025-26 | G20: FY24 p.148; FY25 p.172; FY26 p.173 | H20: Total tax expenses (current + deferred)
A21: Profit for the year | B21: P&L | C21: 2082.05 | D21: 2130.72 | E21: 2561.72 | F21: AR 2023-24 / 2024-25 / 2025-26 | G21: FY24 p.148; FY25 p.172; FY26 p.173
A22: Inventories | B22: Balance sheet | C22: 1075.44 | D22: 1128.9 | E22: 1219.92 | F22: AR 2023-24 / 2024-25 / 2025-26 | G22: FY24 p.147; FY25 p.171; FY26 p.172
A23: Trade receivables | B23: Balance sheet | C23: 347.05 | D23: 379.63 | E23: 404.74 | F23: AR 2023-24 / 2024-25 / 2025-26 | G23: FY24 p.147; FY25 p.171; FY26 p.172
A24: Net cash from operating activities | B24: Cash flow | C24: 2233.73 | D24: 2365.53 | E24: 2546.74 | F24: AR 2023-24 / 2024-25 / 2025-26 | G24: FY24 p.150; FY25 p.174; FY26 p.175 | H24: FY25: AR 2025-26 shows 2,365.53 (restated); AR 2024-25 showed 2,373.15. Newer used.

Sheet Checks
A1: Self-checks on your Data entry (do not edit)
A3: Rounding tolerance: | B3: 0.5 | C3: same unit as Data (e.g. Rs crore). Keep small.
A5: Check | B5: What it tests | C5: =Data!C7 -> FY2023-24 | D5: =Data!D7 -> FY2024-25 | E5: =Data!E7 -> FY2025-26
A6: 1. Expense lines vs Total expenses (difference) | B6: Sum of 7 expense lines minus Total expenses | C6: =IF(COUNT(Data!C10:C17)<8,"",SUM(Data!C10:C16)-Data!C17) -> 1.8189894e-12 | D6: =IF(COUNT(Data!D10:D17)<8,"",SUM(Data!D10:D16)-Data!D17) -> 0 | E6: =IF(COUNT(Data!E10:E17)<8,"",SUM(Data!E10:E16)-Data!E17) -> -1.8189894e-12
A7: 1. Expense lines vs Total expenses (status) | C7: =IF(C6="","Not filled yet",IF(ABS(C6)<=$B$3,"OK","CHECK - find the mistake")) -> OK | D7: =IF(D6="","Not filled yet",IF(ABS(D6)<=$B$3,"OK","CHECK - find the mistake")) -> OK | E7: =IF(E6="","Not filled yet",IF(ABS(E6)<=$B$3,"OK","CHECK - find the mistake")) -> OK
A8: 2. Profit before tax (difference) | B8: Revenue + Other income - Total expenses + Exceptional - PBT | C8: =IF(COUNT(Data!C8:C19)<12,"",Data!C8+Data!C9-Data!C17+Data!C18-Data!C19) -> -1.8189894e-12 | D8: =IF(COUNT(Data!D8:D19)<12,"",Data!D8+Data!D9-Data!D17+Data!D18-Data!D19) -> -2.2737368e-12 | E8: =IF(COUNT(Data!E8:E19)<12,"",Data!E8+Data!E9-Data!E17+Data!E18-Data!E19) -> -1.8189894e-12
A9: 2. Profit before tax (status) | C9: =IF(C8="","Not filled yet",IF(ABS(C8)<=$B$3,"OK","CHECK - find the mistake")) -> OK | D9: =IF(D8="","Not filled yet",IF(ABS(D8)<=$B$3,"OK","CHECK - find the mistake")) -> OK | E9: =IF(E8="","Not filled yet",IF(ABS(E8)<=$B$3,"OK","CHECK - find the mistake")) -> OK
A10: 3. Profit for the year (difference) | B10: PBT - Tax - Profit for the year | C10: =IF(COUNT(Data!C19:C21)<3,"",Data!C19-Data!C20-Data!C21) -> 0 | D10: =IF(COUNT(Data!D19:D21)<3,"",Data!D19-Data!D20-Data!D21) -> 4.5474735e-13 | E10: =IF(COUNT(Data!E19:E21)<3,"",Data!E19-Data!E20-Data!E21) -> 4.5474735e-13
A11: 3. Profit for the year (status) | C11: =IF(C10="","Not filled yet",IF(ABS(C10)<=$B$3,"OK","CHECK - find the mistake")) -> OK | D11: =IF(D10="","Not filled yet",IF(ABS(D10)<=$B$3,"OK","CHECK - find the mistake")) -> OK | E11: =IF(E10="","Not filled yet",IF(ABS(E10)<=$B$3,"OK","CHECK - find the mistake")) -> OK
A13: If check 2 fails only by roughly the exceptional-items amount, you likely entered its sign the wrong way round.

Sheet Analysis
A1: Analysis - you write every formula here (start after all 3 checks show OK)
A2: Tip: reference the Data sheet cells; do not retype numbers. Write each formula in the first year, then check it by hand before copying across.
A4: Block / metric | B4: FY2023-24 | C4: FY2024-25 | D4: FY2025-26 | E4: How I calculated it (write in words)
A5: COMMON-SIZE P&L (% of revenue) | G5: Change in percentage points | H5: (24-25)-(23-24) | I5: (25-26)-(24-25)
A6: Other income | B6: =Data!C9/Data!C8 -> 0.012980907 | C6: =Data!D9/Data!D8 -> 0.014493592 | D6: =Data!E9/Data!E8 -> 0.017263532 | E6: Other income divided by Revenue from operations. | G6: Cost of materials consumed | H6: =C7-B7 -> 0.04086864 | I6: =D7-C7 -> -0.0073347703
A7: Cost of materials consumed | B7: =Data!C10/Data!C$8 -> 0.45685799 | C7: =Data!D10/Data!D8 -> 0.49772663 | D7: =Data!E10/Data!E8 -> 0.49039186 | E7: Cost of materials divided by Revenue from operations. A bigger percentage means more of each ₹100 of sales went on materials. | G7: Purchases of stock-in-trade | H7: =C8-B8 -> -0.010385255 | I7: =D8-C8 -> -0.0052945884
A8: Purchases of stock-in-trade | B8: =Data!C11/Data!C8 -> 0.12562399 | C8: =Data!D11/Data!D8 -> 0.11523874 | D8: =Data!E11/Data!E8 -> 0.10994415 | E8: Purchases of stock-in-trade divided by Revenue from operations. | G8: Changes in inventories | H8: =C9-B9 -> -0.0039298682 | I8: =D9-C9 -> 0.0027680117
A9: Changes in inventories | B9: =Data!C12/Data!C8 -> 6.1781481e-07 | C9: =Data!D12/Data!D8 -> -0.0039292504 | D9: =Data!E12/Data!E8 -> -0.0011612387 | E9: Change in inventories (from the Profit & Loss) divided by Revenue from operations. | G9: Depreciation | H9: =C10-B10 -> -0.00029572503 | I9: =D10-C10 -> 9.4548886e-05
A10: Depreciation | B10: =Data!C15/Data!C8 -> 0.01675452 | C10: =Data!D15/Data!D8 -> 0.016458795 | D10: =Data!E15/Data!E8 -> 0.016553344 | E10: Depreciation divided by Revenue from operations. | G10: Finance cost | H10: =C11-B11 -> -0.0014269914 | I10: =D11-C11 -> -0.001919944
A11: Finance cost | B11: =Data!C14/Data!C8 -> 0.0093537163 | C11: =Data!D14/Data!D8 -> 0.0079267249 | D11: =Data!E14/Data!E8 -> 0.0060067809 | E11: Finance cost divided by Revenue from operations. | G11: Exceptional items | H11: =C12-B12 -> -0.0012541197 | I11: =D12-C12 -> 0.001433286
A12: Exceptional items | B12: =Data!C18/Data!C8 -> -0.0001791663 | C12: =Data!D18/Data!D8 -> -0.001433286 | D12: =Data!E18/Data!E8 -> 0 | E12: Exceptional items divided by Revenue from operations. Negative means an expense. | G12: Tax expense | H12: =C13-B13 -> -0.0051670836 | I12: =D13-C13 -> -0.0029509097
A13: Tax expense | B13: =Data!C20/Data!C8 -> 0.04778118 | C13: =Data!D20/Data!D8 -> 0.042614096 | D13: =Data!E20/Data!E8 -> 0.039663187 | E13: Tax expense divided by Revenue from operations. | G13: Employee benefits expense | H13: =C14-B14 -> -0.0028526884 | I13: =D14-C14 -> 0.0041142865
A14: Employee benefits expense | B14: =Data!C13/Data!C8 -> 0.034923836 | C14: =Data!D13/Data!D8 -> 0.032071147 | D14: =Data!E13/Data!E8 -> 0.036185434 | E14: Employee benefits divided by Revenue from operations. | G14: Other expenses | H14: =C15-B15 -> -0.01111239 | I14: =D15-C15 -> -0.00095942559
A15: Other expenses | B15: =Data!C16/Data!C8 -> 0.19287375 | C15: =Data!D16/Data!D8 -> 0.18176136 | D15: =Data!E16/Data!E8 -> 0.18080194 | E15: Other expenses divided by Revenue from operations.
A16: Profit for the year | B16: =Data!C21/Data!C8 -> 0.12863213 | C16: =Data!D21/Data!D8 -> 0.12319206 | D16: =Data!E21/Data!E8 -> 0.13887808 | E16: Profit for the year divided by Revenue from operations. This is the net margin.
A17: YEAR-ON-YEAR GROWTH
A18: Revenue growth % | B18: N/A | C18: =Data!D8/Data!C8-1 -> 0.068567559 | D18: =Data!E8/Data!D8-1 -> 0.066483888 | E18: This year’s revenue divided by last year’s, minus 1. | G18: profit bridge | H18: 2025-26 bridge | I18: % of last year’s profit | J18: 2024-25 BRIDGE | K18: % of last year’s profit
A19: Profit for the year growth % | B19: N/A | C19: =Data!D21/Data!C21-1 -> 0.023376 | D19: =Data!E21/Data!D21-1 -> 0.20227904 | E19: This year’s profit divided by last year’s, minus 1. | G19: Revenue change | H19: =Data!E8-Data!D8 -> 1149.9 | I19: =H19/Data!D21 -> 0.53967673 | J19: =Data!D8-Data!C8 -> 1109.84 | K19: =J19/Data!C21 -> 0.53305156
A20: Total expenses growth % | B20: N/A | C20: =Data!D17/Data!C17-1 -> 0.082449577 | D20: =Data!E17/Data!D17-1 -> 0.055744354 | E20: This year’s total expenses divided by last year’s, minus 1. | G20: Other income change | H20: =Data!E9-Data!D9 -> 67.76 | I20: =H20/Data!D21 -> 0.031801457 | J20: =Data!D9-Data!C9 -> 40.57 | K20: =J20/Data!C21 -> 0.019485603
A21: RATIOS | G21: Total expenses change | H21: =-(Data!E17-Data!D17) -> -816.88 | I21: =H21/Data!D21 -> -0.38338214 | J21: =-(Data!D17-Data!C17) -> -1116.19 | K21: =J21/Data!C21 -> -0.53610144
A22: Gross margin | B22: =1-(B8+B7+B9) -> 0.4175174 | C22: =1-(C8+C7+C9) -> 0.39096388 | D22: =1-(D8+D7+D9) -> 0.40082523 | E22: A bigger number means more of each ₹100 of sales is left after paying for the product. | G22: Exceptional items change | H22: =Data!E18-Data!D18 -> 24.79 | I22: =H22/Data!D21 -> 0.011634565 | J22: =Data!D18-Data!C18 -> -21.89 | K22: =J22/Data!C21 -> -0.010513676
A23: Operating margin | B23: =(Data!C8-Data!C17+Data!C14)/Data!C8 -> 0.17296529 | C23: =(Data!D8-Data!D17+Data!D14)/Data!D8 -> 0.16067257 | D23: =(Data!E8-Data!E17+Data!E14)/Data!E8 -> 0.16728451 | E23: (Revenue minus total expenses plus finance costs) divided by revenue. Excludes other income and exceptional items. | G23: Tax change | H23: =-(Data!E20-Data!D20) -> 5.43 | I23: =H23/Data!D21 -> 0.0025484343 | J23: =-(Data!D20-Data!C20) -> 36.34 | K23: =J23/Data!C21 -> 0.017453952
A24: Net margin | B24: =B16 -> 0.12863213 | C24: =C16 -> 0.12319206 | D24: =D16 -> 0.13887808 | E24: Same as profit for the year divided by revenue. | G24: Revenue minus expenses change | H24: =H19+H21 -> 333.02 | J24: =J19+J21 -> -6.35
A25: Debtor days | B25: =Data!C23/Data!C8*365 -> 7.826061 | C25: =Data!D23/Data!D8*365 -> 8.0114241 | D25: =Data!E23/Data!E8*365 -> 8.008866 | E25: Trade receivables divided by Revenue from operations, times 365. Uses the year-end balance. A bigger number means customers take longer to pay. | G25: Sum | H25: =SUM(H19:H23) -> 431 | I25: =H25/Data!D21 -> 0.20227904 | J25: =SUM(J19:J23) -> 48.67 | K25: =J25/Data!C21 -> 0.023376
A26: Inventory days | B26: =Data!C22/(Data!C10+Data!C11+Data!C12)*365 -> 41.634601 | C26: =Data!D22/(Data!D10+Data!D11+Data!D12)*365 -> 39.116647 | D26: =Data!E22/(Data!E10+Data!E11+Data!E12)*365 -> 40.287724 | E26: Inventories divided by (materials + purchases + changes in inventories), times 365. Uses the year-end balance. A bigger number means stock sits longer before it is sold. | G26: Actual profit change | H26: =Data!E21-Data!D21 -> 431 | I26: =H26/Data!D21 -> 0.20227904 | J26: =Data!D21-Data!C21 -> 48.67 | K26: =J26/Data!C21 -> 0.023376
A27: Operating cash flow vs profit | B27: =Data!C24/Data!C21 -> 1.0728513 | C27: =Data!D24/Data!D21 -> 1.1102022 | D27: =Data!E24/Data!E21 -> 0.99415237 | E27: Net cash from operating activities divided by Profit for the year. Above 100% means profit came in as cash, and below 100% means some profit did not. | G27: Difference: | H27: 0 | J27: 0

Sheet Dashboard

Sheet Chart data
A1: Component | B1: Change (₹ crore) | D1: Line | E1: FY2024-25 | F1: FY2025-26
A2: Revenue increase | B2: =Data!E8-Data!D8 -> 1149.9 | D2: Materials | E2: =Analysis!H6 -> 0.04086864 | F2: =Analysis!I6 -> -0.0073347703
A3: Other income | B3: =Data!E9-Data!D9 -> 67.76 | D3: Purchases | E3: =Analysis!H7 -> -0.010385255 | F3: =Analysis!I7 -> -0.0052945884
A4: Higher expenses | B4: =Data!D17-Data!E17 -> -816.88 | D4: Employee benefits | E4: =Analysis!H13 -> -0.0028526884 | F4: =Analysis!I13 -> 0.0041142865
A5: Exceptional items | B5: =Data!E18-Data!D18 -> 24.79 | D5: Other expenses | E5: =Analysis!H14 -> -0.01111239 | F5: =Analysis!I14 -> -0.00095942559
A6: Lower tax | B6: =Data!D20-Data!E20 -> 5.43
A7: Profit change | B7: =Data!E21-Data!D21 -> 431
